{"data": {"getLoanAttachments": [{"loanUid": "f73e53f28f824c28aabc19c79b497fd4", "account": "399225858", "name": "ACH Online Payment Terms -202395.pdf", "type": "OTHER", "date": "09/05/2023"}, {"loanUid": "f73e53f28f824c28aabc19c79b497fd4", "account": "399225858", "name": "Payment Statement Report-20230817.pdf", "type": "PAYMENT STATEMENT", "date": "08/17/2023"}, {"loanUid": "f73e53f28f824c28aabc19c79b497fd4", "account": "399225858", "name": "ACH Online Payment Terms -202387.pdf", "type": "OTHER", "date": "08/07/2023"}, {"loanUid": "f73e53f28f824c28aabc19c79b497fd4", "account": "399225858", "name": "Payment Statement Report-20230717.pdf", "type": "PAYMENT STATEMENT", "date": "07/17/2023"}, {"loanUid": "f73e53f28f824c28aabc19c79b497fd4", "account": "399225858", "name": "ACH Online Payment Terms -2023714.pdf", "type": "OTHER", "date": "07/14/2023"}, {"loanUid": "f73e53f28f824c28aabc19c79b497fd4", "account": "399225858", "name": "Notice Letters Report-20230713.pdf", "type": "FIRST LATE", "date": "07/13/2023"}, {"loanUid": "f73e53f28f824c28aabc19c79b497fd4", "account": "399225858", "name": "Payment Statement Report-20230619.pdf", "type": "PAYMENT STATEMENT", "date": "06/19/2023"}, {"loanUid": "f73e53f28f824c28aabc19c79b497fd4", "account": "399225858", "name": "Forbearance Agreement- Valvic Corp Final- not executed.pdf", "type": "OTHER", "date": "06/15/2023"}, {"loanUid": "f73e53f28f824c28aabc19c79b497fd4", "account": "399225858", "name": "ACH Online Payment Terms -2023612.pdf", "type": "OTHER", "date": "06/12/2023"}, {"loanUid": "f73e53f28f824c28aabc19c79b497fd4", "account": "399225858", "name": "invoice_899025978 Valvic 003 .pdf", "type": "OTHER", "date": "05/19/2023"}, {"loanUid": "f73e53f28f824c28aabc19c79b497fd4", "account": "399225858", "name": "Forbearance Agreement- Valvic Corp Final 002 - not executed.pdf", "type": "OTHER", "date": "05/19/2023"}, {"loanUid": "f73e53f28f824c28aabc19c79b497fd4", "account": "399225858", "name": "Payment Statement Report-20230517.pdf", "type": "PAYMENT STATEMENT", "date": "05/17/2023"}, {"loanUid": "f73e53f28f824c28aabc19c79b497fd4", "account": "399225858", "name": "ACH Online Payment Terms -202358.pdf", "type": "OTHER", "date": "05/08/2023"}, {"loanUid": "f73e53f28f824c28aabc19c79b497fd4", "account": "399225858", "name": "Payment Statement Report-20230417.pdf", "type": "PAYMENT STATEMENT", "date": "04/17/2023"}, {"loanUid": "f73e53f28f824c28aabc19c79b497fd4", "account": "399225858", "name": "ACH Online Payment Terms -202347.pdf", "type": "OTHER", "date": "04/07/2023"}, {"loanUid": "f73e53f28f824c28aabc19c79b497fd4", "account": "399225858", "name": "Payment Statement Report-20230317.pdf", "type": "PAYMENT STATEMENT", "date": "03/17/2023"}, {"loanUid": "f73e53f28f824c28aabc19c79b497fd4", "account": "399225858", "name": "ACH Online Payment Terms -202337.pdf", "type": "OTHER", "date": "03/07/2023"}, {"loanUid": "f73e53f28f824c28aabc19c79b497fd4", "account": "399225858", "name": "Payment Statement Report-20230217.pdf", "type": "PAYMENT STATEMENT", "date": "02/17/2023"}, {"loanUid": "f73e53f28f824c28aabc19c79b497fd4", "account": "399225858", "name": "ACH Online Payment Terms -2023210.pdf", "type": "OTHER", "date": "02/10/2023"}, {"loanUid": "f73e53f28f824c28aabc19c79b497fd4", "account": "399225858", "name": "Payment Statement Report-20230117.pdf", "type": "PAYMENT STATEMENT", "date": "01/17/2023"}, {"loanUid": "f73e53f28f824c28aabc19c79b497fd4", "account": "399225858", "name": "ACH Online Payment Terms -202319.pdf", "type": "OTHER", "date": "01/09/2023"}, {"loanUid": "f73e53f28f824c28aabc19c79b497fd4", "account": "399225858", "name": "Borrower Statement Of Account Report-20230104.pdf", "type": "BORROWER STATEMENT OF ACCOUNT", "date": "01/04/2023"}, {"loanUid": "f73e53f28f824c28aabc19c79b497fd4", "account": "399225858", "name": "Payment Statement Report-20221219.pdf", "type": "PAYMENT STATEMENT", "date": "12/19/2022"}, {"loanUid": "f73e53f28f824c28aabc19c79b497fd4", "account": "399225858", "name": "Multiple Loans_Servicing Agreement - Program Select - Lender_2104646.pdf", "type": "ATTACHMENT FROM FILE", "date": "12/06/2022"}, {"loanUid": "f73e53f28f824c28aabc19c79b497fd4", "account": "399225858", "name": "ACH Online Payment Terms -2022125.pdf", "type": "OTHER", "date": "12/05/2022"}, {"loanUid": "f73e53f28f824c28aabc19c79b497fd4", "account": "399225858", "name": "399225858_LATORRE_2022 Tax Bill - PIF.pdf", "type": "OTHER", "date": "12/02/2022"}, {"loanUid": "f73e53f28f824c28aabc19c79b497fd4", "account": "399225858", "name": "AOM + Allonge  BBMOF to PESTANA (002) 3.pdf", "type": "OTHER", "date": "11/22/2022"}, {"loanUid": "f73e53f28f824c28aabc19c79b497fd4", "account": "399225858", "name": "Pestana Capital Setup Form.pdf", "type": "OTHER", "date": "11/22/2022"}, {"loanUid": "f73e53f28f824c28aabc19c79b497fd4", "account": "399225858", "name": "Payment Statement Report-20221118.pdf", "type": "PAYMENT STATEMENT", "date": "11/18/2022"}, {"loanUid": "f73e53f28f824c28aabc19c79b497fd4", "account": "399225858", "name": "Escrow Disclosure-20221117.pdf", "type": "ESCROW DISCLOSURE", "date": "11/17/2022"}, {"loanUid": "f73e53f28f824c28aabc19c79b497fd4", "account": "399225858", "name": "ACH Online Payment Terms -20221110.pdf", "type": "OTHER", "date": "11/10/2022"}, {"loanUid": "f73e53f28f824c28aabc19c79b497fd4", "account": "399225858", "name": "399225858_LATORRE_2022 Tax Bill.pdf", "type": "OTHER", "date": "11/04/2022"}, {"loanUid": "f73e53f28f824c28aabc19c79b497fd4", "account": "399225858", "name": "Payment Statement Report-20221017.pdf", "type": "PAYMENT STATEMENT", "date": "10/17/2022"}, {"loanUid": "f73e53f28f824c28aabc19c79b497fd4", "account": "399225858", "name": "ACH Online Payment Terms -2022107.pdf", "type": "OTHER", "date": "10/07/2022"}, {"loanUid": "f73e53f28f824c28aabc19c79b497fd4", "account": "399225858", "name": "Payment Statement Report-20220919.pdf", "type": "PAYMENT STATEMENT", "date": "09/19/2022"}, {"loanUid": "f73e53f28f824c28aabc19c79b497fd4", "account": "399225858", "name": "ACH Online Payment Terms -202298.pdf", "type": "OTHER", "date": "09/08/2022"}, {"loanUid": "f73e53f28f824c28aabc19c79b497fd4", "account": "399225858", "name": "Payment Statement Report-20220817.pdf", "type": "PAYMENT STATEMENT", "date": "08/17/2022"}, {"loanUid": "f73e53f28f824c28aabc19c79b497fd4", "account": "399225858", "name": "ACH Online Payment Terms -202284.pdf", "type": "OTHER", "date": "08/04/2022"}, {"loanUid": "f73e53f28f824c28aabc19c79b497fd4", "account": "399225858", "name": "Payment Statement Report-20220718.pdf", "type": "PAYMENT STATEMENT", "date": "07/18/2022"}, {"loanUid": "f73e53f28f824c28aabc19c79b497fd4", "account": "399225858", "name": "ACH Online Payment Terms -202276.pdf", "type": "OTHER", "date": "07/06/2022"}, {"loanUid": "f73e53f28f824c28aabc19c79b497fd4", "account": "399225858", "name": "Payment Statement Report-20220617.pdf", "type": "PAYMENT STATEMENT", "date": "06/17/2022"}, {"loanUid": "f73e53f28f824c28aabc19c79b497fd4", "account": "399225858", "name": "Borrower Statement Of Account Report-20220606.pdf", "type": "BORROWER STATEMENT OF ACCOUNT", "date": "06/06/2022"}, {"loanUid": "f73e53f28f824c28aabc19c79b497fd4", "account": "399225858", "name": "ACH Online Payment Terms -202266.pdf", "type": "OTHER", "date": "06/06/2022"}, {"loanUid": "f73e53f28f824c28aabc19c79b497fd4", "account": "399225858", "name": "Payment Statement Report-20220517.pdf", "type": "PAYMENT STATEMENT", "date": "05/17/2022"}, {"loanUid": "f73e53f28f824c28aabc19c79b497fd4", "account": "399225858", "name": "ACH Online Payment Terms -202256.pdf", "type": "OTHER", "date": "05/06/2022"}, {"loanUid": "f73e53f28f824c28aabc19c79b497fd4", "account": "399225858", "name": "Payment Statement Report-20220418.pdf", "type": "PAYMENT STATEMENT", "date": "04/18/2022"}, {"loanUid": "f73e53f28f824c28aabc19c79b497fd4", "account": "399225858", "name": "ACH Online Payment Terms -2022411.pdf", "type": "OTHER", "date": "04/11/2022"}, {"loanUid": "f73e53f28f824c28aabc19c79b497fd4", "account": "399225858", "name": "Payment Statement Report-20220317.pdf", "type": "PAYMENT STATEMENT", "date": "03/17/2022"}, {"loanUid": "f73e53f28f824c28aabc19c79b497fd4", "account": "399225858", "name": "ACH Online Payment Terms -202237.pdf", "type": "OTHER", "date": "03/07/2022"}, {"loanUid": "f73e53f28f824c28aabc19c79b497fd4", "account": "399225858", "name": "Payment Statement Report-20220217.pdf", "type": "PAYMENT STATEMENT", "date": "02/17/2022"}, {"loanUid": "f73e53f28f824c28aabc19c79b497fd4", "account": "399225858", "name": "ACH Online Payment Terms -2022215.pdf", "type": "OTHER", "date": "02/15/2022"}, {"loanUid": "f73e53f28f824c28aabc19c79b497fd4", "account": "399225858", "name": "Notice Letters Report-20220214.pdf", "type": "FIRST LATE", "date": "02/14/2022"}, {"loanUid": "f73e53f28f824c28aabc19c79b497fd4", "account": "399225858", "name": "Borrower Statement Of Account Report-20220126.pdf", "type": "BORROWER STATEMENT OF ACCOUNT", "date": "01/26/2022"}, {"loanUid": "f73e53f28f824c28aabc19c79b497fd4", "account": "399225858", "name": "Payment Statement Report-20220118.pdf", "type": "PAYMENT STATEMENT", "date": "01/18/2022"}, {"loanUid": "f73e53f28f824c28aabc19c79b497fd4", "account": "399225858", "name": "ACH Online Payment Terms -2022110.pdf", "type": "OTHER", "date": "01/10/2022"}, {"loanUid": "f73e53f28f824c28aabc19c79b497fd4", "account": "399225858", "name": "Payment Statement Report-20211217.pdf", "type": "PAYMENT STATEMENT", "date": "12/17/2021"}, {"loanUid": "f73e53f28f824c28aabc19c79b497fd4", "account": "399225858", "name": "ACH Online Payment Terms -2021123.pdf", "type": "OTHER", "date": "12/03/2021"}, {"loanUid": "f73e53f28f824c28aabc19c79b497fd4", "account": "399225858", "name": "Escrow Disclosure-20211119.pdf", "type": "ESCROW DISCLOSURE", "date": "11/19/2021"}, {"loanUid": "f73e53f28f824c28aabc19c79b497fd4", "account": "399225858", "name": "Payment Statement Report-20211117.pdf", "type": "PAYMENT STATEMENT", "date": "11/17/2021"}, {"loanUid": "f73e53f28f824c28aabc19c79b497fd4", "account": "399225858", "name": "399225858_CORP_2021 Tax Bill-PIF.pdf", "type": "OTHER", "date": "11/17/2021"}, {"loanUid": "f73e53f28f824c28aabc19c79b497fd4", "account": "399225858", "name": "ACH Online Payment Terms -2021118.pdf", "type": "OTHER", "date": "11/08/2021"}, {"loanUid": "f73e53f28f824c28aabc19c79b497fd4", "account": "399225858", "name": "multiple_loans_servicing_agreement_2007558-signed.pdf", "type": "ATTACHMENT FROM FILE", "date": "11/05/2021"}, {"loanUid": "f73e53f28f824c28aabc19c79b497fd4", "account": "399225858", "name": "Multiple Loans Servicing Agreement 2007558.pdf", "type": "ATTACHMENT FROM FILE", "date": "11/03/2021"}, {"loanUid": "f73e53f28f824c28aabc19c79b497fd4", "account": "399225858", "name": "399225858_CORP_2021 Tax Bill.pdf", "type": "OTHER", "date": "11/03/2021"}, {"loanUid": "f73e53f28f824c28aabc19c79b497fd4", "account": "399225858", "name": "Payment Statement Report-20211018.pdf", "type": "PAYMENT STATEMENT", "date": "10/18/2021"}, {"loanUid": "f73e53f28f824c28aabc19c79b497fd4", "account": "399225858", "name": "2007558 Setup Form.pdf", "type": "OTHER", "date": "10/07/2021"}, {"loanUid": "f73e53f28f824c28aabc19c79b497fd4", "account": "399225858", "name": "Decimal Capital to Brickell Assignment.pdf", "type": "OTHER", "date": "10/07/2021"}, {"loanUid": "f73e53f28f824c28aabc19c79b497fd4", "account": "399225858", "name": "ACH Online Payment Terms -2021104.pdf", "type": "OTHER", "date": "10/04/2021"}, {"loanUid": "f73e53f28f824c28aabc19c79b497fd4", "account": "399225858", "name": "Payment Statement Report-20210917.pdf", "type": "PAYMENT STATEMENT", "date": "09/17/2021"}, {"loanUid": "f73e53f28f824c28aabc19c79b497fd4", "account": "399225858", "name": "ACH Online Payment Terms -202197.pdf", "type": "OTHER", "date": "09/07/2021"}, {"loanUid": "f73e53f28f824c28aabc19c79b497fd4", "account": "399225858", "name": "Payment Statement Report-20210817.pdf", "type": "PAYMENT STATEMENT", "date": "08/17/2021"}, {"loanUid": "f73e53f28f824c28aabc19c79b497fd4", "account": "399225858", "name": "ACH Online Payment Terms -202185.pdf", "type": "OTHER", "date": "08/05/2021"}, {"loanUid": "f73e53f28f824c28aabc19c79b497fd4", "account": "399225858", "name": "Payment Statement Report-20210719.pdf", "type": "PAYMENT STATEMENT", "date": "07/19/2021"}, {"loanUid": "f73e53f28f824c28aabc19c79b497fd4", "account": "399225858", "name": "ACH Online Payment Terms -202176.pdf", "type": "OTHER", "date": "07/06/2021"}, {"loanUid": "f73e53f28f824c28aabc19c79b497fd4", "account": "399225858", "name": "Payment Statement Report-20210617.pdf", "type": "PAYMENT STATEMENT", "date": "06/17/2021"}, {"loanUid": "f73e53f28f824c28aabc19c79b497fd4", "account": "399225858", "name": "Notice Letters Report-20210613.pdf", "type": "FIRST LATE", "date": "06/13/2021"}, {"loanUid": "f73e53f28f824c28aabc19c79b497fd4", "account": "399225858", "name": "Payment Statement Report-20210517.pdf", "type": "PAYMENT STATEMENT", "date": "05/17/2021"}, {"loanUid": "f73e53f28f824c28aabc19c79b497fd4", "account": "399225858", "name": "Payment Statement Report-20210419.pdf", "type": "PAYMENT STATEMENT", "date": "04/19/2021"}, {"loanUid": "f73e53f28f824c28aabc19c79b497fd4", "account": "399225858", "name": "Payment Statement Report-20210317.pdf", "type": "PAYMENT STATEMENT", "date": "03/17/2021"}, {"loanUid": "f73e53f28f824c28aabc19c79b497fd4", "account": "399225858", "name": "Notice Letters Report-20210315.pdf", "type": "FIRST LATE", "date": "03/15/2021"}, {"loanUid": "f73e53f28f824c28aabc19c79b497fd4", "account": "399225858", "name": "Notice Letters Report-20210222.pdf", "type": "SECOND LATE", "date": "02/22/2021"}, {"loanUid": "f73e53f28f824c28aabc19c79b497fd4", "account": "399225858", "name": "Notice Letters Report-20210218.pdf", "type": "FIRST LATE", "date": "02/18/2021"}, {"loanUid": "f73e53f28f824c28aabc19c79b497fd4", "account": "399225858", "name": "Payment Statement Report-20210217.pdf", "type": "PAYMENT STATEMENT", "date": "02/17/2021"}, {"loanUid": "f73e53f28f824c28aabc19c79b497fd4", "account": "399225858", "name": "Notice Letters Report-20210201.pdf", "type": "FIFTH LATE", "date": "02/01/2021"}, {"loanUid": "f73e53f28f824c28aabc19c79b497fd4", "account": "399225858", "name": "Borrower Statement Of Account Report-20210120.pdf", "type": "BORROWER STATEMENT OF ACCOUNT", "date": "01/20/2021"}, {"loanUid": "f73e53f28f824c28aabc19c79b497fd4", "account": "399225858", "name": "Payment Statement Report-20210119.pdf", "type": "PAYMENT STATEMENT", "date": "01/19/2021"}, {"loanUid": "f73e53f28f824c28aabc19c79b497fd4", "account": "399225858", "name": "Notice Letters Report-20210101.pdf", "type": "THIRD LATE", "date": "01/01/2021"}, {"loanUid": "f73e53f28f824c28aabc19c79b497fd4", "account": "399225858", "name": "Notice Letters Report-20201223.pdf", "type": "SECOND LATE", "date": "12/23/2020"}, {"loanUid": "f73e53f28f824c28aabc19c79b497fd4", "account": "399225858", "name": "Payment Statement Report-20201217.pdf", "type": "PAYMENT STATEMENT", "date": "12/17/2020"}, {"loanUid": "f73e53f28f824c28aabc19c79b497fd4", "account": "399225858", "name": "Notice Letters Report-20201202.pdf", "type": "THIRD LATE", "date": "12/02/2020"}, {"loanUid": "f73e53f28f824c28aabc19c79b497fd4", "account": "399225858", "name": "399225858_VALIC CORP_2020 Tax Bill - PIF.pdf", "type": "OTHER", "date": "11/25/2020"}, {"loanUid": "f73e53f28f824c28aabc19c79b497fd4", "account": "399225858", "name": "Notice Letters Report-20201123.pdf", "type": "SECOND LATE", "date": "11/23/2020"}, {"loanUid": "f73e53f28f824c28aabc19c79b497fd4", "account": "399225858", "name": "Payment Statement Report-20201117.pdf", "type": "PAYMENT STATEMENT", "date": "11/17/2020"}, {"loanUid": "f73e53f28f824c28aabc19c79b497fd4", "account": "399225858", "name": "Notice Letters Report-20201116.pdf", "type": "FIRST LATE", "date": "11/16/2020"}, {"loanUid": "f73e53f28f824c28aabc19c79b497fd4", "account": "399225858", "name": "Escrow Disclosure-20201109.pdf", "type": "ESCROW DISCLOSURE", "date": "11/09/2020"}, {"loanUid": "f73e53f28f824c28aabc19c79b497fd4", "account": "399225858", "name": "399225858_VALIC CORP_2020 Tax Bill.pdf", "type": "OTHER", "date": "11/04/2020"}, {"loanUid": "f73e53f28f824c28aabc19c79b497fd4", "account": "399225858", "name": "Notice Letters Report-20201022.pdf", "type": "SECOND LATE", "date": "10/22/2020"}, {"loanUid": "f73e53f28f824c28aabc19c79b497fd4", "account": "399225858", "name": "Payment Statement Report-20201019.pdf", "type": "PAYMENT STATEMENT", "date": "10/19/2020"}, {"loanUid": "f73e53f28f824c28aabc19c79b497fd4", "account": "399225858", "name": "Notice Letters Report-20201014.pdf", "type": "FIRST LATE", "date": "10/14/2020"}, {"loanUid": "f73e53f28f824c28aabc19c79b497fd4", "account": "399225858", "name": "Notice Letters Report-20201002.pdf", "type": "THIRD LATE", "date": "10/02/2020"}, {"loanUid": "f73e53f28f824c28aabc19c79b497fd4", "account": "399225858", "name": "Notice Letters Report-20200923.pdf", "type": "SECOND LATE", "date": "09/23/2020"}, {"loanUid": "f73e53f28f824c28aabc19c79b497fd4", "account": "399225858", "name": "Payment Statement Report-20200917.pdf", "type": "PAYMENT STATEMENT", "date": "09/17/2020"}, {"loanUid": "f73e53f28f824c28aabc19c79b497fd4", "account": "399225858", "name": "Notice Letters Report-20200915.pdf", "type": "FIRST LATE", "date": "09/15/2020"}, {"loanUid": "f73e53f28f824c28aabc19c79b497fd4", "account": "399225858", "name": "Notice Letters Report-20200901.pdf", "type": "THIRD LATE", "date": "09/01/2020"}, {"loanUid": "f73e53f28f824c28aabc19c79b497fd4", "account": "399225858", "name": "Notice Letters Report-20200824.pdf", "type": "SECOND LATE", "date": "08/24/2020"}, {"loanUid": "f73e53f28f824c28aabc19c79b497fd4", "account": "399225858", "name": "Payment Statement Report-20200817.pdf", "type": "PAYMENT STATEMENT", "date": "08/17/2020"}, {"loanUid": "f73e53f28f824c28aabc19c79b497fd4", "account": "399225858", "name": "Notice Letters Report-20200812.pdf", "type": "FIRST LATE", "date": "08/12/2020"}, {"loanUid": "f73e53f28f824c28aabc19c79b497fd4", "account": "399225858", "name": "Borrower Statement Of Account Report-20200731.pdf", "type": "BORROWER STATEMENT OF ACCOUNT", "date": "07/31/2020"}, {"loanUid": "f73e53f28f824c28aabc19c79b497fd4", "account": "399225858", "name": "Payment Statement Report-20200717.pdf", "type": "PAYMENT STATEMENT", "date": "07/17/2020"}, {"loanUid": "f73e53f28f824c28aabc19c79b497fd4", "account": "399225858", "name": "Notice Letters Report-20200702.pdf", "type": "THIRD LATE", "date": "07/02/2020"}, {"loanUid": "f73e53f28f824c28aabc19c79b497fd4", "account": "399225858", "name": "Notice Letters Report-20200622.pdf", "type": "SECOND LATE", "date": "06/22/2020"}, {"loanUid": "f73e53f28f824c28aabc19c79b497fd4", "account": "399225858", "name": "Payment Statement Report-20200617.pdf", "type": "PAYMENT STATEMENT", "date": "06/17/2020"}, {"loanUid": "f73e53f28f824c28aabc19c79b497fd4", "account": "399225858", "name": "Notice Letters Report-20200612.pdf", "type": "FIRST LATE", "date": "06/12/2020"}, {"loanUid": "f73e53f28f824c28aabc19c79b497fd4", "account": "399225858", "name": "Payment Statement Report-20200519.pdf", "type": "PAYMENT STATEMENT", "date": "05/19/2020"}, {"loanUid": "f73e53f28f824c28aabc19c79b497fd4", "account": "399225858", "name": "Notice Letters Report-20200512.pdf", "type": "FIRST LATE", "date": "05/12/2020"}, {"loanUid": "f73e53f28f824c28aabc19c79b497fd4", "account": "399225858", "name": "Payment Statement Report-20200417.pdf", "type": "PAYMENT STATEMENT", "date": "04/17/2020"}, {"loanUid": "f73e53f28f824c28aabc19c79b497fd4", "account": "399225858", "name": "Payment Statement Report-20200317.pdf", "type": "PAYMENT STATEMENT", "date": "03/17/2020"}, {"loanUid": "f73e53f28f824c28aabc19c79b497fd4", "account": "399225858", "name": "Payment Statement Report-20200219.pdf", "type": "PAYMENT STATEMENT", "date": "02/19/2020"}, {"loanUid": "f73e53f28f824c28aabc19c79b497fd4", "account": "399225858", "name": "Borrower Statement Of Account Report-20200130.pdf", "type": "BORROWER STATEMENT OF ACCOUNT", "date": "01/30/2020"}, {"loanUid": "f73e53f28f824c28aabc19c79b497fd4", "account": "399225858", "name": "Borrower Statement Of Account Report-20200129.pdf", "type": "BORROWER STATEMENT OF ACCOUNT", "date": "01/29/2020"}, {"loanUid": "f73e53f28f824c28aabc19c79b497fd4", "account": "399225858", "name": "399225858_LATORRE_Property Tax Refund from County.pdf", "type": "OTHER", "date": "01/21/2020"}, {"loanUid": "f73e53f28f824c28aabc19c79b497fd4", "account": "399225858", "name": "Payment Statement Report-20200117.pdf", "type": "PAYMENT STATEMENT", "date": "01/17/2020"}, {"loanUid": "f73e53f28f824c28aabc19c79b497fd4", "account": "399225858", "name": "Escrow Disclosure-20200101.pdf", "type": "ESCROW DISCLOSURE", "date": "01/01/2020"}, {"loanUid": "f73e53f28f824c28aabc19c79b497fd4", "account": "399225858", "name": "Payment Statement Report-20191217.pdf", "type": "PAYMENT STATEMENT", "date": "12/17/2019"}, {"loanUid": "f73e53f28f824c28aabc19c79b497fd4", "account": "399225858", "name": "399225858_LATORRE_2019 Tax Bill - PIF.pdf", "type": "OTHER", "date": "11/26/2019"}, {"loanUid": "f73e53f28f824c28aabc19c79b497fd4", "account": "399225858", "name": "Payment Statement Report-20191119.pdf", "type": "PAYMENT STATEMENT", "date": "11/19/2019"}, {"loanUid": "f73e53f28f824c28aabc19c79b497fd4", "account": "399225858", "name": "Escrow Disclosure-20191108.pdf", "type": "ESCROW DISCLOSURE", "date": "11/08/2019"}, {"loanUid": "f73e53f28f824c28aabc19c79b497fd4", "account": "399225858", "name": "399225858_LATORRE_2019 Tax Bill.pdf", "type": "OTHER", "date": "11/08/2019"}, {"loanUid": "f73e53f28f824c28aabc19c79b497fd4", "account": "399225858", "name": "Payment Statement Report-20191017.pdf", "type": "PAYMENT STATEMENT", "date": "10/17/2019"}, {"loanUid": "f73e53f28f824c28aabc19c79b497fd4", "account": "399225858", "name": "Payment Statement Report-20190917.pdf", "type": "PAYMENT STATEMENT", "date": "09/17/2019"}, {"loanUid": "f73e53f28f824c28aabc19c79b497fd4", "account": "399225858", "name": "Updated Broker Spread Assignment DECIMAL CAPITAL PARTNERS LLC FCI SETUP FORM.pdf", "type": "OTHER", "date": "08/23/2019"}, {"loanUid": "f73e53f28f824c28aabc19c79b497fd4", "account": "399225858", "name": "Payment Statement Report-20190817.pdf", "type": "PAYMENT STATEMENT", "date": "08/17/2019"}, {"loanUid": "f73e53f28f824c28aabc19c79b497fd4", "account": "399225858", "name": "DECIMAL CAPITAL PARTNERS LLC FCI ASSIGNMENT SETUP FORM CORRECTED.pdf", "type": "OTHER", "date": "08/14/2019"}, {"loanUid": "f73e53f28f824c28aabc19c79b497fd4", "account": "399225858", "name": "Notice Letters Report-20190813.pdf", "type": "FIRST LATE", "date": "08/13/2019"}, {"loanUid": "f73e53f28f824c28aabc19c79b497fd4", "account": "399225858", "name": "Payment Statement Report-20190717.pdf", "type": "PAYMENT STATEMENT", "date": "07/17/2019"}, {"loanUid": "f73e53f28f824c28aabc19c79b497fd4", "account": "399225858", "name": "Notice Letters Report-20190624.pdf", "type": "SECOND LATE", "date": "06/24/2019"}, {"loanUid": "f73e53f28f824c28aabc19c79b497fd4", "account": "399225858", "name": "Payment Statement Report-20190618.pdf", "type": "PAYMENT STATEMENT", "date": "06/18/2019"}, {"loanUid": "f73e53f28f824c28aabc19c79b497fd4", "account": "399225858", "name": "Servicing Agreement Signed Multi Loans 1902694-3.pdf", "type": "ATTACHMENT FROM FILE", "date": "06/14/2019"}, {"loanUid": "f73e53f28f824c28aabc19c79b497fd4", "account": "399225858", "name": "Notice Letters Report-20190612.pdf", "type": "FIRST LATE", "date": "06/12/2019"}, {"loanUid": "f73e53f28f824c28aabc19c79b497fd4", "account": "399225858", "name": "Servicing Agreement - Standard 1902694-3.pdf", "type": "ATTACHMENT FROM FILE", "date": "05/29/2019"}, {"loanUid": "f73e53f28f824c28aabc19c79b497fd4", "account": "399225858", "name": "Payment Statement Report-20190517.pdf", "type": "PAYMENT STATEMENT", "date": "05/17/2019"}, {"loanUid": "f73e53f28f824c28aabc19c79b497fd4", "account": "399225858", "name": "399225858 VALVIC CORP rec Mortgage.pdf", "type": "OTHER", "date": "05/14/2019"}, {"loanUid": "f73e53f28f824c28aabc19c79b497fd4", "account": "399225858", "name": "Notice Letters Report-20190513.pdf", "type": "FIRST LATE", "date": "05/13/2019"}, {"loanUid": "f73e53f28f824c28aabc19c79b497fd4", "account": "399225858", "name": "DECIMAL CAPITAL PARTNERS LLC FCI SETUP FORM.pdf", "type": "OTHER", "date": "05/10/2019"}, {"loanUid": "f73e53f28f824c28aabc19c79b497fd4", "account": "399225858", "name": "399225858 - VALVIC CORP ASSIGNMENT.pdf", "type": "OTHER", "date": "05/10/2019"}, {"loanUid": "f73e53f28f824c28aabc19c79b497fd4", "account": "399225858", "name": "399225858 - assingment - VALVIC CORP.pdf", "type": "OTHER", "date": "05/07/2019"}, {"loanUid": "f73e53f28f824c28aabc19c79b497fd4", "account": "399225858", "name": "Payment Statement Report-20190417.pdf", "type": "PAYMENT STATEMENT", "date": "04/17/2019"}, {"loanUid": "f73e53f28f824c28aabc19c79b497fd4", "account": "399225858", "name": "Notice Letters Report-20190322.pdf", "type": "SECOND LATE", "date": "03/22/2019"}, {"loanUid": "f73e53f28f824c28aabc19c79b497fd4", "account": "399225858", "name": "Payment Statement Report-20190319.pdf", "type": "PAYMENT STATEMENT", "date": "03/19/2019"}, {"loanUid": "f73e53f28f824c28aabc19c79b497fd4", "account": "399225858", "name": "Escrow Disclosure-20190319.pdf", "type": "ESCROW DISCLOSURE", "date": "03/19/2019"}, {"loanUid": "f73e53f28f824c28aabc19c79b497fd4", "account": "399225858", "name": "Notice Letters Report-20190312.pdf", "type": "FIRST LATE", "date": "03/12/2019"}, {"loanUid": "f73e53f28f824c28aabc19c79b497fd4", "account": "399225858", "name": "225858 Servicing Agreement Signed 13333.pdf", "type": "OTHER", "date": "02/19/2019"}, {"loanUid": "f73e53f28f824c28aabc19c79b497fd4", "account": "399225858", "name": "Servicing Agreement - Standard.pdf", "type": "OTHER", "date": "02/15/2019"}, {"loanUid": "f73e53f28f824c28aabc19c79b497fd4", "account": "399225858", "name": "Lender Welcome Letter - Lender.pdf", "type": "OTHER", "date": "02/15/2019"}, {"loanUid": "f73e53f28f824c28aabc19c79b497fd4", "account": "399225858", "name": "Boarding - Welcome Package (New Loan) - Borrower", "type": "OTHER", "date": "02/14/2019"}, {"loanUid": "f73e53f28f824c28aabc19c79b497fd4", "account": "399225858", "name": "Payment Statement Report-20190214.pdf", "type": "PAYMENT STATEMENT", "date": "02/14/2019"}, {"loanUid": "f73e53f28f824c28aabc19c79b497fd4", "account": "399225858", "name": "Tax Bill.pdf", "type": "IMPORT ATTACHMENTS", "date": "02/08/2019"}, {"loanUid": "f73e53f28f824c28aabc19c79b497fd4", "account": "399225858", "name": "Setup Form.pdf", "type": "IMPORT ATTACHMENTS", "date": "02/08/2019"}, {"loanUid": "f73e53f28f824c28aabc19c79b497fd4", "account": "399225858", "name": "Note.pdf", "type": "IMPORT ATTACHMENTS", "date": "02/08/2019"}, {"loanUid": "f73e53f28f824c28aabc19c79b497fd4", "account": "399225858", "name": "Mortgage.pdf", "type": "IMPORT ATTACHMENTS", "date": "02/08/2019"}, {"loanUid": "f73e53f28f824c28aabc19c79b497fd4", "account": "399225858", "name": "HUD-1.pdf", "type": "IMPORT ATTACHMENTS", "date": "02/08/2019"}, {"loanUid": "f73e53f28f824c28aabc19c79b497fd4", "account": "399225858", "name": "EOI.pdf", "type": "IMPORT ATTACHMENTS", "date": "02/08/2019"}, {"loanUid": "f73e53f28f824c28aabc19c79b497fd4", "account": "399225858", "name": "Email.pdf", "type": "IMPORT ATTACHMENTS", "date": "02/08/2019"}, {"loanUid": "f73e53f28f824c28aabc19c79b497fd4", "account": "399225858", "name": "1003.pdf", "type": "IMPORT ATTACHMENTS", "date": "02/08/2019"}]}}